core/__init__.py
core/algo.py
test/__init__.py
test/algo_test.py
zi_dct0-0.0.8.dist-info/METADATA
zi_dct0-0.0.8.dist-info/RECORD
zi_dct0-0.0.8.dist-info/WHEEL
zi_dct0-0.0.8.dist-info/top_level.txt
