Metadata-Version: 2.1
Name: zi-dct0
Version: 0.0.8
Summary: ZI DCT0 implementation in python
Home-page: https://github.com/kiennt23/zi_dct0.git
Author: Kien Nguyen
Author-email: kiennt23@gmail.com
License: UNKNOWN
Platform: UNKNOWN
Classifier: Programming Language :: Python :: 3
Classifier: License :: OSI Approved :: GNU General Public License v3 (GPLv3)
Classifier: Operating System :: OS Independent
